finder_sidebar_editor/FinderSidebarEditor.py
finder_sidebar_editor/__init__.py
finder_sidebar_editor/__main__.py
finder_sidebar_editor-1.2.0.dist-info/LICENSE
finder_sidebar_editor-1.2.0.dist-info/METADATA
finder_sidebar_editor-1.2.0.dist-info/WHEEL
finder_sidebar_editor-1.2.0.dist-info/entry_points.txt
finder_sidebar_editor-1.2.0.dist-info/top_level.txt
finder_sidebar_editor-1.2.0.dist-info/RECORD
