Metadata-Version: 2.1
Name: finder-sidebar-editor
Version: 1.2.0
Summary: Module for editing the Favorites entries of the Finder sidebar.
Home-page: https://github.com/Ajordat/finder-sidebar-editor
Author: Ajordat
Author-email: alexjortri@gmail.com
Maintainer: Ajordat
Maintainer-email: alexjortri@gmail.com
License: MIT
Platform: UNKNOWN
Classifier: License :: OSI Approved :: MIT License
Classifier: Programming Language :: Python :: 3.7
License-File: LICENSE
Requires-Dist: pyobjc
